kafka_lmdc/demo.py
kafka_lmdc/kafka.py
kafka_lmdc-2.0.5.dist-info/LICENSE
kafka_lmdc-2.0.5.dist-info/METADATA
kafka_lmdc-2.0.5.dist-info/WHEEL
kafka_lmdc-2.0.5.dist-info/entry_points.txt
kafka_lmdc-2.0.5.dist-info/top_level.txt
kafka_lmdc-2.0.5.dist-info/RECORD
