Metadata-Version: 2.1
Name: kafka-lmdc
Version: 2.0.5
Summary: Esta biblioteca tem como objetivo a facilitação do uso de Kerberos e Kafka em Python. (Agregando max.poll.interval.ms no consumer na versao 2.0.5)
Home-page: https://github.com/LMDC-UFF/kafka-python
Author: LMDC-UFF
Author-email: opensource@lmdc.uff.br
License: MIT
Platform: UNKNOWN
Classifier: License :: OSI Approved :: MIT License
Classifier: Programming Language :: Python :: 3
Classifier: Programming Language :: Python :: 3.6
Classifier: Programming Language :: Python :: 3.7
Classifier: Programming Language :: Python :: 3.8
Requires-Dist: confluent-kafka
